mmget/__init__.py
mmget/downloader.py
mmget/downloadspeedestimator.py
mmget/errors.py
mmget/formatter.py
mmget/outputpathmetadata.py
mmget/partedfilewriter.py
mmget/threadpool.py
mmget/types.py
mmget/url.py
mmget/reporters/__init__.py
mmget/reporters/ipyreporter.py
mmget/reporters/printreporter.py
mmget/reporters/reporter.py
mmget/reporters/reporterfactory.py
mmget/reporters/threadsafereporter.py
mmget/tasks/__init__.py
mmget/tasks/civitaitask.py
mmget/tasks/dummytask.py
mmget/tasks/huggingfacetask.py
mmget/tasks/invalidtask.py
mmget/tasks/regularlinktask.py
mmget/tasks/task.py
mmget/tasks/taskfactory.py
mmget-0.1.1.dist-info/LICENSE
mmget-0.1.1.dist-info/METADATA
mmget-0.1.1.dist-info/WHEEL
mmget-0.1.1.dist-info/top_level.txt
mmget-0.1.1.dist-info/RECORD
