Metadata-Version: 2.1
Name: mmget
Version: 0.1.1
Summary: Multi Model Get - A library to download files from various sources including Hugging Face and Civitai
Home-page: https://github.com/benlau/mmget
Author: Ben Lau
Author-email: xbenlau@gmail.com
License: UNKNOWN
Platform: UNKNOWN
Classifier: Development Status :: 3 - Alpha
Classifier: Intended Audience :: Developers
Classifier: License :: OSI Approved :: MIT License
Classifier: Operating System :: OS Independent
Classifier: Programming Language :: Python :: 3
Classifier: Programming Language :: Python :: 3.6
Classifier: Programming Language :: Python :: 3.7
Classifier: Programming Language :: Python :: 3.8
Classifier: Programming Language :: Python :: 3.9
Requires-Python: >=3.6
License-File: LICENSE
Requires-Dist: requests>=2.25.1
